tests/test_emic2.py
tests/__init__.py
tests/smoke_tests/test_commands.py
tests/smoke_tests/__init__.py
zorg_emic/emic2.py
zorg_emic/__init__.py
zorg_emic/adaptors.py
zorg_emic-0.0.3.dist-info/RECORD
zorg_emic-0.0.3.dist-info/top_level.txt
zorg_emic-0.0.3.dist-info/metadata.json
zorg_emic-0.0.3.dist-info/zip-safe
zorg_emic-0.0.3.dist-info/METADATA
zorg_emic-0.0.3.dist-info/DESCRIPTION.rst
zorg_emic-0.0.3.dist-info/WHEEL
