Metadata-Version: 2.0
Name: zorg-emic
Version: 0.0.3
Summary: Python library for the Emic 2 Text to Speech Module.
Home-page: https://github.com/zorg/zorg-emic
Author: Zorg Group
Author-email: gunthercx@gmail.com
License: MIT
Keywords: zorg,emic,emic2
Platform: any
Classifier: Development Status :: 4 - Beta
Classifier: Intended Audience :: Developers
Classifier: License :: OSI Approved :: BSD License
Classifier: Environment :: Console
Classifier: Environment :: Web Environment
Classifier: Operating System :: OS Independent
Classifier: Programming Language :: Python
Classifier: Programming Language :: Python :: 2
Classifier: Programming Language :: Python :: 2.7
Classifier: Programming Language :: Python :: 3
Classifier: Programming Language :: Python :: 3.3
Classifier: Programming Language :: Python :: 3.4
Requires-Dist: zorg (>=0.0.3,<0.1.0)
Requires-Dist: pyserial (<4.0.0)
